caster.py
setup.py
caster.egg-info/PKG-INFO
caster.egg-info/SOURCES.txt
caster.egg-info/dependency_links.txt
caster.egg-info/entry_points.txt
caster.egg-info/requires.txt
caster.egg-info/top_level.txt