Metadata-Version: 1.1
Name: caster
Version: 0.1
Summary: Caster is a command line tool for casting media to chromecast
Home-page: https://github.com/palaviv/caster
Author: Aviv Palivoda
Author-email: palaviv@gmail.com
License: MIT
Download-URL: https://github.com/palaviv/caster/tarball/0.1
Platform: UNKNOWN
